mongoelector/__init__.py
mongoelector/elector.py
mongoelector/locker.py
mongoelector-0.6.1.dist-info/DESCRIPTION.rst
mongoelector-0.6.1.dist-info/METADATA
mongoelector-0.6.1.dist-info/RECORD
mongoelector-0.6.1.dist-info/WHEEL
mongoelector-0.6.1.dist-info/metadata.json
mongoelector-0.6.1.dist-info/top_level.txt
