Metadata-Version: 2.0
Name: mongoelector
Version: 0.6.1
Summary: Distributed master election and locking in mongodb
Home-page: https://github.com/zebpalmer/mongoelector
Author: Zeb Palmer
Author-email: zeb@zebpalmer.com
License: GPLv3
Keywords: mongoelector
Platform: UNKNOWN
Classifier: Development Status :: 4 - Beta
Classifier: Intended Audience :: Developers
Classifier: License :: OSI Approved :: GNU Lesser General Public License v3 or later (LGPLv3+)
Classifier: Natural Language :: English
Classifier: Programming Language :: Python :: 2
Classifier: Programming Language :: Python :: 2.7
Classifier: Programming Language :: Python :: 3
Classifier: Programming Language :: Python :: 3.4
Classifier: Programming Language :: Python :: 3.5
Requires-Dist: pymongo
